[
  {
    "requirement": 0,
    "requirementType": "",
    "Equivalencies": [
      {
        "Destination": [
          [
            {
              "courseName": "Industrial Costs and Controls",
              "courseID": "IME 239",
              "units": 3.0
            }
          ]
        ],
        "Source": [
          [
            {
              "courseName": "No course articulated",
              "courseID": "",
              "units": 0
            }
          ]
        ],
        "relationToNext": "OR"
      },
      {
        "Destination": [
          [
            {
              "courseName": "Financial Accounting for Decision Making",
              "courseID": "ACC 207",
              "units": 4.0
            },
            {
              "courseName": "Financial Accounting for Decision Making",
              "courseID": "ACC 207A",
              "units": 1.0
            }
          ]
        ],
        "Source": [
          [
            {
              "courseName": "Financial Accounting I",
              "courseID": "ACCT 1A",
              "units": 5.0
            }
          ],
          [
            {
              "courseName": "Financial Accounting I - HONORS",
              "courseID": "ACCT 1AH",
              "units": 5.0
            }
          ],
          [
            {
              "courseName": "Financial Accounting II",
              "courseID": "ACCT 1B",
              "units": 5.0
            }
          ],
          [
            {
              "courseName": "Financial Accounting II - HONORS",
              "courseID": "ACCT 1BH",
              "units": 5.0
            }
          ]
        ],
        "relationToNext": "OR"
      },
      {
        "Destination": [
          [
            {
              "courseName": "Accounting for Agribusiness",
              "courseID": "ABM 224",
              "units": 4.0
            }
          ]
        ],
        "Source": [
          [
            {
              "courseName": "No Comparable Course",
              "courseID": "",
              "units": 0
            }
          ]
        ],
        "relationToNext": ""
      }
    ]
  },
  {
    "requirement": 0,
    "requirementType": "",
    "Equivalencies": [
      {
        "Destination": [
          [
            {
              "courseName": "Agriculture and the Modern World",
              "courseID": "AG 101",
              "units": 4.0
            }
          ]
        ],
        "Source": [
          [
            {
              "courseName": "No course articulated",
              "courseID": "",
              "units": 0
            }
          ]
        ],
        "relationToNext": ""
      }
    ]
  },
  {
    "requirement": 0,
    "requirementType": "",
    "Equivalencies": [
      {
        "Destination": [
          [
            {
              "courseName": "Elementary Statistics with Applications",
              "courseID": "STA 120",
              "units": 4.0
            }
          ]
        ],
        "Source": [
          [
            {
              "courseName": "Elementary Statistics and Probability",
              "courseID": "MATH 10",
              "units": 5.0
            }
          ],
          [
            {
              "courseName": "Elementary Statistics and Probability - HONORS",
              "courseID": "MATH 10H",
              "units": 5.0
            }
          ]
        ],
        "relationToNext": ""
      }
    ]
  },
  {
    "requirement": 0,
    "requirementType": "",
    "Equivalencies": [
      {
        "Destination": [
          [
            {
              "courseName": "Consumer Chemistry",
              "courseID": "CHM 101",
              "units": 3.0
            },
            {
              "courseName": "Consumer Chemistry (Lab)",
              "courseID": "CHM 101L",
              "units": 1.0
            }
          ]
        ],
        "Source": [
          [
            {
              "courseName": "No course articulated",
              "courseID": "",
              "units": 0
            }
          ]
        ],
        "relationToNext": "OR"
      },
      {
        "Destination": [
          [
            {
              "courseName": "Fundamentals of Physics",
              "courseID": "PHY 102",
              "units": 4.0
            }
          ]
        ],
        "Source": [
          [
            {
              "courseName": "No course articulated",
              "courseID": "",
              "units": 0
            }
          ]
        ],
        "relationToNext": ""
      }
    ]
  },
  {
    "requirement": 0,
    "requirementType": "",
    "Equivalencies": [
      {
        "Destination": [
          [
            {
              "courseName": "General Chemistry",
              "courseID": "CHM 121",
              "units": 3.0
            },
            {
              "courseName": "General Chemistry Laboratory",
              "courseID": "CHM 121L",
              "units": 1.0
            },
            {
              "courseName": "General Chemistry",
              "courseID": "CHM 122",
              "units": 3.0
            },
            {
              "courseName": "General Chemistry Laboratory",
              "courseID": "CHM 122L",
              "units": 1.0
            },
            {
              "courseName": "General Chemistry",
              "courseID": "CHM 123",
              "units": 3.0
            },
            {
              "courseName": "General Chemistry Laboratory",
              "courseID": "CHM 123L",
              "units": 1.0
            }
          ]
        ],
        "Source": [
          [
            {
              "courseName": "General Chemistry",
              "courseID": "CHEM 1A",
              "units": 5.0
            },
            {
              "courseName": "General Chemistry",
              "courseID": "CHEM 1B",
              "units": 5.0
            },
            {
              "courseName": "General Chemistry and Qualitative Analysis",
              "courseID": "CHEM 1C",
              "units": 5.0
            }
          ]
        ],
        "relationToNext": ""
      }
    ]
  },
  {
    "requirement": 0,
    "requirementType": "",
    "Equivalencies": [
      {
        "Destination": [
          [
            {
              "courseName": "Culture, People, and Dress",
              "courseID": "AMM 108",
              "units": 4.0
            }
          ]
        ],
        "Source": [
          [
            {
              "courseName": "No course articulated",
              "courseID": "",
              "units": 0
            }
          ]
        ],
        "relationToNext": ""
      }
    ]
  },
  {
    "requirement": 0,
    "requirementType": "",
    "Equivalencies": [
      {
        "Destination": [
          [
            {
              "courseName": "American Demographics and Lifestyles",
              "courseID": "AMM 120",
              "units": 4.0
            }
          ]
        ],
        "Source": [
          [
            {
              "courseName": "No Comparable Course",
              "courseID": "",
              "units": 0
            }
          ]
        ],
        "relationToNext": ""
      }
    ]
  },
  {
    "requirement": 0,
    "requirementType": "",
    "Equivalencies": [
      {
        "Destination": [
          [
            {
              "courseName": "Consumerism: Impact and Issues",
              "courseID": "AMM 245",
              "units": 4.0
            }
          ]
        ],
        "Source": [
          [
            {
              "courseName": "No Comparable Course",
              "courseID": "",
              "units": 0
            }
          ]
        ],
        "relationToNext": ""
      }
    ]
  },
  {
    "requirement": 0,
    "requirementType": "",
    "Equivalencies": [
      {
        "Destination": [
          [
            {
              "courseName": "Visual Merchandising/Store Design I",
              "courseID": "AMM 270",
              "units": 2.0
            },
            {
              "courseName": "Visual Merchandising/Store Design I",
              "courseID": "AMM 270A",
              "units": 2.0
            }
          ]
        ],
        "Source": [
          [
            {
              "courseName": "No course articulated",
              "courseID": "",
              "units": 0
            }
          ]
        ],
        "relationToNext": ""
      }
    ]
  },
  {
    "requirement": 0,
    "requirementType": "",
    "Equivalencies": [
      {
        "Destination": [
          [
            {
              "courseName": "Introduction to Microcomputing",
              "courseID": "CIS 101",
              "units": 4.0
            }
          ]
        ],
        "Source": [
          [
            {
              "courseName": "Business Information Systems",
              "courseID": "CIS 3",
              "units": 4.5
            }
          ]
        ],
        "relationToNext": ""
      }
    ]
  },
  {
    "requirement": 0,
    "requirementType": "",
    "Equivalencies": [
      {
        "Destination": [
          [
            {
              "courseName": "Principles of Economics",
              "courseID": "EC 201",
              "units": 4.0
            }
          ]
        ],
        "Source": [
          [
            {
              "courseName": "Principles of Microeconomics",
              "courseID": "ECON 2",
              "units": 4.0
            }
          ],
          [
            {
              "courseName": "Principles of Microeconomics - HONORS",
              "courseID": "ECON 2H",
              "units": 4.0
            }
          ]
        ],
        "relationToNext": "OR"
      },
      {
        "Destination": [
          [
            {
              "courseName": "Principles of Economics",
              "courseID": "EC 202",
              "units": 4.0
            }
          ]
        ],
        "Source": [
          [
            {
              "courseName": "Principles of Macroeconomics",
              "courseID": "ECON 1",
              "units": 4.0
            }
          ],
          [
            {
              "courseName": "Principles of Macroeconomics - HONORS",
              "courseID": "ECON 1H",
              "units": 4.0
            }
          ]
        ],
        "relationToNext": ""
      }
    ]
  },
  {
    "requirement": 0,
    "requirementType": "",
    "Equivalencies": [
      {
        "Destination": [
          [
            {
              "courseName": "Legal Environment of Business-Transactions",
              "courseID": "FRL 201",
              "units": 4.0
            }
          ]
        ],
        "Source": [
          [
            {
              "courseName": "Business Law I",
              "courseID": "BUS 18",
              "units": 5.0
            }
          ]
        ],
        "relationToNext": ""
      }
    ]
  },
  {
    "requirement": 0,
    "requirementType": "",
    "Equivalencies": [
      {
        "Destination": [
          [
            {
              "courseName": "Elementary Spanish I",
              "courseID": "SPN 151",
              "units": 4.0
            }
          ]
        ],
        "Source": [
          [
            {
              "courseName": "Elementary Spanish (First Quarter)",
              "courseID": "SPAN 1",
              "units": 5.0
            }
          ]
        ],
        "relationToNext": "OR"
      },
      {
        "Destination": [
          [
            {
              "courseName": "Elementary Chinese I",
              "courseID": "FL 171",
              "units": 4.0
            }
          ]
        ],
        "Source": [
          [
            {
              "courseName": "Elementary Mandarin (First Quarter)",
              "courseID": "MAND 1",
              "units": 5.0
            }
          ]
        ],
        "relationToNext": ""
      }
    ]
  },
  {
    "requirement": 0,
    "requirementType": "",
    "Equivalencies": [
      {
        "Destination": [
          [
            {
              "courseName": "Apparel Retailing",
              "courseID": "AMM 296",
              "units": 4.0
            }
          ]
        ],
        "Source": [
          [
            {
              "courseName": "No course articulated",
              "courseID": "",
              "units": 0
            }
          ]
        ],
        "relationToNext": ""
      }
    ]
  },
  {
    "requirement": 0,
    "requirementType": "",
    "Equivalencies": [
      {
        "Destination": [
          [
            {
              "courseName": "Fashion Industry",
              "courseID": "AMM 101",
              "units": 4.0
            }
          ]
        ],
        "Source": [
          [
            {
              "courseName": "No course articulated",
              "courseID": "",
              "units": 0
            }
          ]
        ],
        "relationToNext": ""
      }
    ]
  },
  {
    "requirement": 0,
    "requirementType": "",
    "Equivalencies": [
      {
        "Destination": [
          [
            {
              "courseName": "Digital Illustration for Fashion",
              "courseID": "AMM 112L",
              "units": 2.0
            }
          ]
        ],
        "Source": [
          [
            {
              "courseName": "No Comparable Course",
              "courseID": "",
              "units": 0
            }
          ]
        ],
        "relationToNext": ""
      }
    ]
  },
  {
    "requirement": 0,
    "requirementType": "",
    "Equivalencies": [
      {
        "Destination": [
          [
            {
              "courseName": "Introduction to Textile Sciences",
              "courseID": "AMM 160",
              "units": 3.0
            },
            {
              "courseName": "Introduction to Textile Science Lab",
              "courseID": "AMM 160L",
              "units": 1.0
            }
          ]
        ],
        "Source": [
          [
            {
              "courseName": "No course articulated",
              "courseID": "",
              "units": 0
            }
          ]
        ],
        "relationToNext": ""
      }
    ]
  },
  {
    "requirement": 0,
    "requirementType": "",
    "Equivalencies": [
      {
        "Destination": [
          [
            {
              "courseName": "Apparel Construction Lab",
              "courseID": "AMM 180L",
              "units": 1.0
            }
          ]
        ],
        "Source": [
          [
            {
              "courseName": "No course articulated",
              "courseID": "",
              "units": 0
            }
          ]
        ],
        "relationToNext": ""
      }
    ]
  },
  {
    "requirement": 0,
    "requirementType": "",
    "Equivalencies": [
      {
        "Destination": [
          [
            {
              "courseName": "Apparel Design Analysis",
              "courseID": "AMM 210",
              "units": 2.0
            },
            {
              "courseName": "Apparel Design Analysis",
              "courseID": "AMM 210A",
              "units": 2.0
            }
          ]
        ],
        "Source": [
          [
            {
              "courseName": "No course articulated",
              "courseID": "",
              "units": 0
            }
          ]
        ],
        "relationToNext": ""
      }
    ]
  },
  {
    "requirement": 0,
    "requirementType": "",
    "Equivalencies": [
      {
        "Destination": [
          [
            {
              "courseName": "Fashion Promotion",
              "courseID": "AMM 230",
              "units": 3.0
            }
          ]
        ],
        "Source": [
          [
            {
              "courseName": "No course articulated",
              "courseID": "",
              "units": 0
            }
          ]
        ],
        "relationToNext": ""
      }
    ]
  },
  {
    "requirement": 0,
    "requirementType": "",
    "Equivalencies": [
      {
        "Destination": [
          [
            {
              "courseName": "Apparel Merchandise Buying I",
              "courseID": "AMM 251",
              "units": 3.0
            },
            {
              "courseName": "Apparel Merchandise Buying I Activity",
              "courseID": "AMM 251A",
              "units": 1.0
            }
          ]
        ],
        "Source": [
          [
            {
              "courseName": "No course articulated",
              "courseID": "",
              "units": 0
            }
          ]
        ],
        "relationToNext": ""
      }
    ]
  },
  {
    "requirement": 0,
    "requirementType": "",
    "Equivalencies": [
      {
        "Destination": [
          [
            {
              "courseName": "Textile Fabrications",
              "courseID": "AMM 260",
              "units": 3.0
            },
            {
              "courseName": "Textile Fabrications - Laboratory",
              "courseID": "AMM 260L",
              "units": 1.0
            }
          ]
        ],
        "Source": [
          [
            {
              "courseName": "No course articulated",
              "courseID": "",
              "units": 0
            }
          ]
        ],
        "relationToNext": ""
      }
    ]
  }
]